Metadata-Version: 2.1
Name: example-package-terminator-363
Version: 0.0.1
Summary: Demo Project for Mentorskool assigned training.
Author-email: Ashish Singh <ashishsinghshekhawat41@gmail.com>
Project-URL: Homepage, https://github.com/pypa/sampleproject
Project-URL: Bug Tracker, https://github.com/pypa/sampleproject/issues
Classifier: Programming Language :: Python :: 3
Classifier: License :: OSI Approved :: MIT License
Requires-Python: >=3.7
License-File: LICENSE
Requires-Dist: pandas
Requires-Dist: numpy
Requires-Dist: requests
Requires-Dist: argparse
